tagtog/__init__.py
tagtog-0.1.1.dist-info/WHEEL
tagtog-0.1.1.dist-info/METADATA
tagtog-0.1.1.dist-info/RECORD
